eralchemy/__init__.py
eralchemy/cst.py
eralchemy/helpers.py
eralchemy/main.py
eralchemy/models.py
eralchemy/parser.py
eralchemy/py.typed
eralchemy/sqla.py
eralchemy-1.5.0.dist-info/LICENSE
eralchemy-1.5.0.dist-info/METADATA
eralchemy-1.5.0.dist-info/WHEEL
eralchemy-1.5.0.dist-info/entry_points.txt
eralchemy-1.5.0.dist-info/top_level.txt
eralchemy-1.5.0.dist-info/RECORD
