Metadata-Version: 2.1
Name: eralchemy
Version: 1.5.0
Summary: Simple entity relation (ER) diagrams generation
Author-email: Alexis Benoist <Alexis-benoist@users.noreply.github.com>, Florian Maurer <fmaurer@disroot.org>
License: Apache-2.0
Project-URL: homepage, https://github.com/eralchemy/eralchemy
Project-URL: repository, https://github.com/eralchemy/eralchemy
Keywords: sql,ORM,relational databases,ER diagram,render
Classifier: Development Status :: 5 - Production/Stable
Classifier: Intended Audience :: Developers
Classifier: Operating System :: OS Independent
Classifier: Topic :: Scientific/Engineering :: Visualization
Classifier: Topic :: Software Development :: Libraries :: Python Modules
Classifier: Topic :: Database
Requires-Python: >=3.8
License-File: LICENSE
Requires-Dist: sqlalchemy>=1.4.18
Provides-Extra: test
Requires-Dist: flask-sqlalchemy>=2.5.1; extra == "test"
Requires-Dist: psycopg2>=2.9.3; extra == "test"
Requires-Dist: pytest>=7.4.3; extra == "test"
Requires-Dist: pytest-cov; extra == "test"
Requires-Dist: pygraphviz>=1.9; extra == "test"
Requires-Dist: graphviz>=0.20.3; extra == "test"
Provides-Extra: graphviz
Requires-Dist: graphviz>=0.20.3; extra == "graphviz"
Provides-Extra: pygraphviz
Requires-Dist: pygraphviz>=1.9; extra == "pygraphviz"
Provides-Extra: dev
Requires-Dist: nox; extra == "dev"
Requires-Dist: pre-commit; extra == "dev"
Provides-Extra: docs
Requires-Dist: sphinx>=6.2.1; extra == "docs"
Requires-Dist: pydata-sphinx-theme; extra == "docs"
Requires-Dist: sphinx-copybutton; extra == "docs"
Requires-Dist: sphinx-design; extra == "docs"
